fastapi_gen/__init__.py
fastapi_gen/cli.py
fastapi_gen/config.py
fastapi_gen/generator.py
fastapi_gen/prompts.py
fastapi_gen/template/VARIABLES.md
fastapi_gen/template/cookiecutter.json
fastapi_gen/template/hooks/post_gen_project.py
fastapi_gen/template/{{cookiecutter.project_slug}}/.env.prod.example
fastapi_gen/template/{{cookiecutter.project_slug}}/.gitignore
fastapi_gen/template/{{cookiecutter.project_slug}}/.gitlab-ci.yml
fastapi_gen/template/{{cookiecutter.project_slug}}/AGENTS.md
fastapi_gen/template/{{cookiecutter.project_slug}}/CLAUDE.md
fastapi_gen/template/{{cookiecutter.project_slug}}/Makefile
fastapi_gen/template/{{cookiecutter.project_slug}}/README.md
fastapi_gen/template/{{cookiecutter.project_slug}}/docker-compose.dev.yml
fastapi_gen/template/{{cookiecutter.project_slug}}/docker-compose.frontend.yml
fastapi_gen/template/{{cookiecutter.project_slug}}/docker-compose.prod.yml
fastapi_gen/template/{{cookiecutter.project_slug}}/docker-compose.yml
fastapi_gen/template/{{cookiecutter.project_slug}}/.github/workflows/ci.yml
fastapi_gen/template/{{cookiecutter.project_slug}}/backend/.dockerignore
fastapi_gen/template/{{cookiecutter.project_slug}}/backend/.env.example
fastapi_gen/template/{{cookiecutter.project_slug}}/backend/.pre-commit-config.yaml
fastapi_gen/template/{{cookiecutter.project_slug}}/backend/Dockerfile
fastapi_gen/template/{{cookiecutter.project_slug}}/backend/alembic.ini
fastapi_gen/template/{{cookiecutter.project_slug}}/backend/pyproject.toml
fastapi_gen/template/{{cookiecutter.project_slug}}/backend/alembic/env.py
fastapi_gen/template/{{cookiecutter.project_slug}}/backend/alembic/script.py.mako
fastapi_gen/template/{{cookiecutter.project_slug}}/backend/alembic/versions/.gitkeep
fastapi_gen/template/{{cookiecutter.project_slug}}/backend/app/__init__.py
fastapi_gen/template/{{cookiecutter.project_slug}}/backend/app/admin.py
fastapi_gen/template/{{cookiecutter.project_slug}}/backend/app/main.py
fastapi_fullstack-0.1.18.dist-info/METADATA
fastapi_fullstack-0.1.18.dist-info/WHEEL
fastapi_fullstack-0.1.18.dist-info/entry_points.txt
fastapi_fullstack-0.1.18.dist-info/licenses/LICENSE
fastapi_fullstack-0.1.18.dist-info/RECORD
