Metadata-Version: 2.4
Name: fastapi-fullstack
Version: 0.1.18
Summary: Full-stack FastAPI + Next.js template generator with PydanticAI/LangChain agents, WebSocket streaming, 20+ enterprise integrations, and Logfire/LangSmith observability. Ship AI apps fast. CLI tool to generate production-ready FastAPI + Next.js projects with AI agents, auth, and observability.
Project-URL: Homepage, https://github.com/vstorm-co/full-stack-fastapi-nextjs-llm-template
Project-URL: Documentation, https://github.com/vstorm-co/full-stack-fastapi-nextjs-llm-template#readme
Project-URL: Repository, https://github.com/vstorm-co/full-stack-fastapi-nextjs-llm-template
Author-email: Vstorm <hr@vstorm.co>
License: MIT
License-File: LICENSE
Keywords: ai-agents,celery,cookiecutter,docker,fastapi,full-stack,langchain,langgraph,llm,logfire,mongodb,nextjs,observability,postgresql,pydantic-ai,python,react,redis,template,typescript
Classifier: Development Status :: 3 - Alpha
Classifier: Environment :: Console
Classifier: Framework :: FastAPI
Classifier: Intended Audience :: Developers
Classifier: License :: OSI Approved :: MIT License
Classifier: Programming Language :: Python :: 3
Classifier: Programming Language :: Python :: 3.11
Classifier: Programming Language :: Python :: 3.12
Classifier: Topic :: Software Development :: Code Generators
Requires-Python: >=3.11
Requires-Dist: click>=8.1.0
Requires-Dist: cookiecutter>=2.6.0
Requires-Dist: email-validator>=2.0.0
Requires-Dist: pydantic-settings>=2.0.0
Requires-Dist: pydantic>=2.0.0
Requires-Dist: questionary>=2.0.0
Requires-Dist: rich>=13.0.0
Provides-Extra: dev
Requires-Dist: mypy>=1.13.0; extra == 'dev'
Requires-Dist: pre-commit>=3.0.0; extra == 'dev'
Requires-Dist: pytest-cov>=4.0.0; extra == 'dev'
Requires-Dist: pytest>=8.0.0; extra == 'dev'
Requires-Dist: ruff>=0.8.0; extra == 'dev'
Provides-Extra: docs
Requires-Dist: mkdocs-material>=9.5.0; extra == 'docs'
Requires-Dist: mkdocs>=1.6.0; extra == 'docs'
Requires-Dist: pymdown-extensions>=10.0.0; extra == 'docs'
